cryptocompare/__init__.py
cryptocompare/cryptocompare.py
cryptocompare_fields-0.1.1.dist-info/LICENSE
cryptocompare_fields-0.1.1.dist-info/METADATA
cryptocompare_fields-0.1.1.dist-info/WHEEL
cryptocompare_fields-0.1.1.dist-info/top_level.txt
cryptocompare_fields-0.1.1.dist-info/RECORD
