Metadata-Version: 2.1
Name: cryptocompare-fields
Version: 0.1.1
Summary: Wrapper for CryptoCompare.com
Home-page: https://github.com/LambertoKalisto/CryptoCompare
Author: lamberto
Author-email: dhgdgjdjhd@gmail.com
License: MIT
Keywords: crypto cryptocurrency wrapper cryptocompare
Classifier: Programming Language :: Python :: 3
Requires-Python: >=3
License-File: LICENSE
Requires-Dist: requests
